giakiethoang/__init__.py
giakiethoang-1.0.dist-info/METADATA
giakiethoang-1.0.dist-info/WHEEL
giakiethoang-1.0.dist-info/top_level.txt
giakiethoang-1.0.dist-info/RECORD
