Metadata-Version: 2.4
Name: giakiethoang
Version: 1.0
Summary: by Hoàng Gia Kiệt, Trương Quang Thắng
Author-email: <quangthangctii@gmail.com>
License: Eclipse Public License 2.0
Keywords: cli,fade,colors,terminal,tui
Dynamic: author-email
Dynamic: description
Dynamic: keywords
Dynamic: license
Dynamic: summary
